<Properties>
  <MonoDevelop.Ide.Workbench ActiveDocument="Embeddinator-Registrar-Interop/Class1.cs">
    <Files>
      <File FileName="Embeddinator-Registrar-Interop/Class1.cs" Line="13" Column="11" />
    </Files>
    <Pads>
      <Pad Id="ProjectPad">
        <State name="__root__">
          <Node name="Embeddinator-Registrar-Interop" expanded="True">
            <Node name="Embeddinator-Registrar-Interop" expanded="True" selected="True">
              <Node name="Dependencies" expanded="True" />
            </Node>
          </Node>
        </State>
      </Pad>
    </Pads>
  </MonoDevelop.Ide.Workbench>
  <MonoDevelop.Ide.DebuggingService.PinnedWatches />
  <MonoDevelop.Ide.Workspace ActiveConfiguration="Release" />
  <MonoDevelop.Ide.DebuggingService.Breakpoints>
    <BreakpointStore />
  </MonoDevelop.Ide.DebuggingService.Breakpoints>
  <MultiItemStartupConfigurations />
</Properties>